vnstock_ezchart/__init__.py
vnstock_ezchart/config.py
vnstock_ezchart/mplot.py
vnstock_ezchart/utils.py
vnstock_ezchart-0.0.1.dist-info/LICENSE
vnstock_ezchart-0.0.1.dist-info/METADATA
vnstock_ezchart-0.0.1.dist-info/WHEEL
vnstock_ezchart-0.0.1.dist-info/top_level.txt
vnstock_ezchart-0.0.1.dist-info/RECORD
