Metadata-Version: 2.1
Name: vnstock_ezchart
Version: 0.0.1
Summary: A comprehensive wrapper for Matplotlib, Seaborn which designed to provide a fast, simple, and efficient user experience for routine data visualization tasks
Home-page: https://github.com/vnstock-hq/vnstock_ezchart
Author: Thinh Vu
Author-email: mrthinh@live.com
Requires-Python: >=3.7
License-File: LICENSE
Requires-Dist: squarify
Requires-Dist: wordcloud
Requires-Dist: vnstock
Requires-Dist: requests
Requires-Dist: openpyxl
